pypapago/__init__.py
pypapago/translator.py
pypapago-0.1.1.1.dist-info/LICENSE
pypapago-0.1.1.1.dist-info/METADATA
pypapago-0.1.1.1.dist-info/WHEEL
pypapago-0.1.1.1.dist-info/top_level.txt
pypapago-0.1.1.1.dist-info/RECORD
