Metadata-Version: 2.1
Name: pypapago
Version: 0.1.1.1
Summary: [Unofficial] Python wrapper for Papago translation service
Home-page: https://github.com/Beomi/pypapago
Author: Junbum Lee
Author-email: jun@beomi.net
License: MIT
Platform: UNKNOWN
Classifier: Programming Language :: Python :: 3
Classifier: License :: OSI Approved :: MIT License
Classifier: Operating System :: OS Independent
Requires-Dist: requests (<3)
Requires-Dist: tqdm (<5)
